{"schemaVersion":"protocol-lab-package-v2","packageId":"org.protocol-lab.components.implementation.grpc-java-netty","packageVersion":"0.1.1","kind":"implementation","displayName":"gRPC Java Netty Target","entryManifests":["implementations/grpc-java-netty.yaml"],"providedImplementations":[{"implementationId":"grpc-java-netty","displayName":"gRPC Java Netty Target","protocols":["h2"],"scenarios":["grpc.h2.deadline-exceeded","grpc.h2.client-cancellation"]}],"dependencies":{"requiredCapabilities":[{"name":"docker","value":"true"}]}}
